{"intents": [
    {"tag": "tuition",
        "patterns": [
        "What is the tuition for a CS course?", 
        "What is tuition per course?", 
        "How much does a course cost?",
        "What is the tution?"
        ],
        "responses": [
        "Around 700 bucks per course. Not expensive at all ;)",
        ],
        "context": [""]
    },
    {"tag": "courses",
        "patterns": [
        "How many courses do I need for my degree?",
        "What courses do I need to take for CS?",
        "What are the required courses?"
        ],
        "responses": [
        "Too many, you will be our gest for the next 6 years :)",
        ],
        "context": [""]
    },
    {"tag": "trash-talk",
        "patterns": [
        "You are a bad bot.",
        "I'm mad at you",
        ""
        ],
        "responses": [
        "It is always my plesure", "Couldn't care less"
        ],
        "context": [""]
    }
   ]
}
